ws2811_mqtt/__init__.py
ws2811_mqtt/args/__init__.py
ws2811_mqtt/device_config.yaml
ws2811_mqtt/leds/__init__.py
ws2811_mqtt/logger/__init__.py
ws2811_mqtt/mqtt/__init__.py
ws2811_mqtt/utils/__init__.py
ws2811_mqtt-1.3.1.dist-info/METADATA
ws2811_mqtt-1.3.1.dist-info/WHEEL
ws2811_mqtt-1.3.1.dist-info/entry_points.txt
ws2811_mqtt-1.3.1.dist-info/RECORD
